qubiter/BitVector.py
qubiter/CGateExpander.py
qubiter/CGateSEO_writer.pdf
qubiter/CGateSEO_writer.py
qubiter/CktEmbedder.py
qubiter/CodaSEO_writer.py
qubiter/Controls.py
qubiter/EchoingSEO_reader.py
qubiter/FouSEO_writer.py
qubiter/HadamardTransform.py
qubiter/LICENSE.md
qubiter/LoopFileGenerator.py
qubiter/LoopyPlaceholderManager.py
qubiter/OneBitGates.py
qubiter/PlaceholderManager.py
qubiter/Plotter.py
qubiter/SEO_Lista.py
qubiter/SEO_MatrixProduct.py
qubiter/SEO_pre_reader.py
qubiter/SEO_reader.py
qubiter/SEO_simulator.py
qubiter/SEO_simulator_tf.py
qubiter/SEO_writer.py
qubiter/StateVec.py
qubiter/UnitaryMat.py
qubiter/__init__.py
qubiter/qubiter_rosetta_stone.pdf
qubiter/qubiter_rosetta_stone.tex
qubiter/run_all_nb.py
qubiter/run_all_py.py
qubiter/utilities_gen.py
qubiter/adv_applications/CostMinimizer.py
qubiter/adv_applications/MeanHamil.py
qubiter/adv_applications/MeanHamilMinimizer.py
qubiter/adv_applications/MeanHamil_native.py
qubiter/adv_applications/MeanHamil_rigetti.py
qubiter/adv_applications/PhaseEstSEO_writer.py
qubiter/adv_applications/StairsAllDeriv_native.py
qubiter/adv_applications/StairsAllDeriv_rigetti.py
qubiter/adv_applications/StairsCkt_writer.py
qubiter/adv_applications/StairsDeriv.py
qubiter/adv_applications/StairsDerivCkt_writer.py
qubiter/adv_applications/StairsDerivThrCkt_writer.py
qubiter/adv_applications/StairsDeriv_native.py
qubiter/adv_applications/StairsDeriv_rigetti.py
qubiter/adv_applications/__init__.py
qubiter/adv_applications/five_easy_pieces.pdf
qubiter/adv_applications/five_easy_pieces.tex
qubiter/adv_applications/setup_autograd.py
qubiter/adv_applications/threaded_grad.pdf
qubiter/adv_applications/threaded_grad.tex
qubiter/device_specific/ChipCouplingsFitter.py
qubiter/device_specific/ForbiddenCNotExpander.py
qubiter/device_specific/QbitPlanarLattice.py
qubiter/device_specific/Qubiter_to_AnyQasm.py
qubiter/device_specific/Qubiter_to_GoogleCirq.py
qubiter/device_specific/Qubiter_to_IBMqasm.py
qubiter-1.0.1.dist-info/LICENSE.md
qubiter-1.0.1.dist-info/METADATA
qubiter-1.0.1.dist-info/WHEEL
qubiter-1.0.1.dist-info/top_level.txt
qubiter-1.0.1.dist-info/RECORD
