Metadata-Version: 2.1
Name: qubiter
Version: 1.0.1
Summary: Python tools for reading, writing, compiling, simulating quantum computer circuits.
Home-page: https://github.com/artiste-qb-net/qubiter
Author: qubiter contributors
Author-email: rrtucci@gmail.com
License: UNKNOWN
Keywords: quantum compiler
Platform: UNKNOWN
Classifier: Programming Language :: Python :: 3
Classifier: License :: OSI Approved :: BSD License
Classifier: Operating System :: OS Independent
Requires-Dist: numpy
Requires-Dist: scipy
